pi_eltakows_webthing/__init__.py
pi_eltakows_webthing/app.py
pi_eltakows_webthing/eltako.py
pi_eltakows_webthing/eltako_webthing.py
pi_eltakows_webthing-1.1.7.dist-info/LICENSE
pi_eltakows_webthing-1.1.7.dist-info/METADATA
pi_eltakows_webthing-1.1.7.dist-info/WHEEL
pi_eltakows_webthing-1.1.7.dist-info/entry_points.txt
pi_eltakows_webthing-1.1.7.dist-info/top_level.txt
pi_eltakows_webthing-1.1.7.dist-info/RECORD
