Metadata-Version: 2.1
Name: pi-eltakows-webthing
Version: 1.1.7
Summary: A web connected Eltako windsensor measuring wind speed on Raspberry Pi
Home-page: https://github.com/grro/pi_eltakows_webthing
Author: Gregor Roth
Author-email: gregor.roth@web.de
License: MIT
Keywords: webthings,home automation,Eltako,windsensor,windspeed,WS,raspberry,pi
Platform: UNKNOWN
Classifier: Programming Language :: Python :: 3
Classifier: License :: OSI Approved :: Apache Software License
Classifier: Operating System :: OS Independent
Classifier: Development Status :: 3 - Alpha
Requires-Dist: webthing >=0.15.0
Requires-Dist: RPi.GPIO
